agent_guard/__init__.py
agent_guard/cost_calculator.py
agent_guard/logger.py
agent_guard/monitor.py
agent_guard/utils.py
agent_guard/visualizer.py
tests/__init__.py
tests/test_agent_guard.py
agent_guard-0.1.7.dist-info/LICENSE
agent_guard-0.1.7.dist-info/METADATA
agent_guard-0.1.7.dist-info/WHEEL
agent_guard-0.1.7.dist-info/top_level.txt
agent_guard-0.1.7.dist-info/RECORD
