Metadata-Version: 2.1
Name: agent-guard
Version: 0.1.7
Summary: An operational monitoring library for Crew AI applications.
Home-page: https://github.com/rajparmarr2308/agent-guard
Author: Raj Parmar
Author-email: rajparmar2308@gmail.com
Classifier: Programming Language :: Python :: 3
Classifier: License :: OSI Approved :: MIT License
Classifier: Operating System :: OS Independent
Requires-Python: >=3.8
License-File: LICENSE
Requires-Dist: psutil
Requires-Dist: matplotlib
Requires-Dist: streamlit
Requires-Dist: tiktoken
